pyflipper/__init__.py
pyflipper/pyflipper.py
pyflipper/lib/__init__.py
pyflipper/lib/bt.py
pyflipper/lib/date.py
pyflipper/lib/debug.py
pyflipper/lib/device_info.py
pyflipper/lib/free.py
pyflipper/lib/gpio.py
pyflipper/lib/i2c.py
pyflipper/lib/ikey.py
pyflipper/lib/input.py
pyflipper/lib/ir.py
pyflipper/lib/led.py
pyflipper/lib/loader.py
pyflipper/lib/log.py
pyflipper/lib/music_player.py
pyflipper/lib/nfc.py
pyflipper/lib/onewire.py
pyflipper/lib/power.py
pyflipper/lib/ps.py
pyflipper/lib/rfid.py
pyflipper/lib/serial_wrapper.py
pyflipper/lib/storage.py
pyflipper/lib/subghz.py
pyflipper/lib/threaded.py
pyflipper/lib/update.py
pyflipper/lib/utils.py
pyflipper/lib/vibro.py
pyflipper-0.21.dist-info/licenses/LICENSE
pyflipper-0.21.dist-info/METADATA
pyflipper-0.21.dist-info/WHEEL
pyflipper-0.21.dist-info/top_level.txt
pyflipper-0.21.dist-info/RECORD
